Starfish/__init__.py
Starfish/constants.py
Starfish/spectrum.py
Starfish/transforms.py
Starfish/utils.py
Starfish/emulator/__init__.py
Starfish/emulator/_utils.py
Starfish/emulator/emulator.py
Starfish/emulator/kernels.py
Starfish/emulator/plotting.py
Starfish/grid_tools/__init__.py
Starfish/grid_tools/base_interfaces.py
Starfish/grid_tools/instruments.py
Starfish/grid_tools/interfaces.py
Starfish/grid_tools/interpolators.py
Starfish/grid_tools/utils.py
Starfish/models/__init__.py
Starfish/models/echelle_model.py
Starfish/models/kernels.py
Starfish/models/spectrum_model.py
Starfish/models/utils.py
astrostarfish-0.4.2.dist-info/LICENSE
astrostarfish-0.4.2.dist-info/METADATA
astrostarfish-0.4.2.dist-info/WHEEL
astrostarfish-0.4.2.dist-info/top_level.txt
astrostarfish-0.4.2.dist-info/RECORD
