Metadata-Version: 2.1
Name: astrostarfish
Version: 0.4.2
Summary: Covariance tools for fitting stellar spectra
Author: Ian Czekala
Author-email: iancze@gmail.com
Maintainer: Miles Lucas <mdlucas@hawaii.edu
License: BSD-4-Clause
Project-URL: repository, https://github.com/iancze/Starfish
Project-URL: documentation, https://starfish.rtfd.io
Keywords: Science Astronomy Physics Data Science
Classifier: Intended Audience :: Science/Research
Classifier: Programming Language :: Python :: 3
Classifier: Topic :: Scientific/Engineering :: Astronomy
Classifier: Topic :: Scientific/Engineering :: Physics
Requires-Python: >=3.7,<3.10
License-File: LICENSE
Requires-Dist: astropy (<6,>=4)
Requires-Dist: dataclasses (<0.7,>=0.6)
Requires-Dist: extinction (==0.4.*)
Requires-Dist: flatdict (==4.*)
Requires-Dist: h5py (==3.*)
Requires-Dist: nptyping (==1.*)
Requires-Dist: numpy (<2,>=1.16)
Requires-Dist: scikit-learn (<2,>=0.22)
Requires-Dist: scipy (<2,>=1.3.0)
Requires-Dist: toml (<0.11,>=0.10.1)
Requires-Dist: tqdm (==4.*)
Provides-Extra: docs
Requires-Dist: nbsphinx (==0.*,>=0.4.2) ; extra == 'docs'
Requires-Dist: pandoc (==2.*) ; extra == 'docs'
Requires-Dist: sphinx (==2.*) ; extra == 'docs'
Requires-Dist: sphinx-bootstrap-theme (==0.*,>=0.7.1) ; extra == 'docs'
Requires-Dist: IPython ; extra == 'docs'
Requires-Dist: sphinx-autodoc-typehints (==1.10.3) ; extra == 'docs'
Provides-Extra: test
Requires-Dist: coveralls (==1.*,>=1.8.0) ; extra == 'test'
Requires-Dist: pytest (==4.*,>=4.6.0) ; extra == 'test'
Requires-Dist: pytest-black ; extra == 'test'
Requires-Dist: pytest-cov (==2.*,>=2.7.0) ; extra == 'test'
Requires-Dist: pytest-benchmark ; extra == 'test'
